ImageDataAugmentor/__init__.py
ImageDataAugmentor/config.py
ImageDataAugmentor/config.yaml
ImageDataAugmentor/image_data_augmentation.py
ImageDataAugmentor/utils.py
ImageDataAugmentor/augmentors/color_augmentor.py
ImageDataAugmentor/augmentors/noise_augmentor.py
ImageDataAugmentor/augmentors/position_augmentor.py
ImageDataAugmentor/augmentors/__pycache__/color_augmentor.cpython-310.pyc
ImageDataAugmentor/augmentors/__pycache__/noise_augmentor.cpython-310.pyc
ImageDataAugmentor/augmentors/__pycache__/position_augmentor.cpython-310.pyc
ImageDataAugmentor/configs/color_config.py
ImageDataAugmentor/configs/noise_config.py
ImageDataAugmentor/configs/position_config.py
ImageDataAugmentor/configs/__pycache__/color_config.cpython-310.pyc
ImageDataAugmentor/configs/__pycache__/noise_config.cpython-310.pyc
ImageDataAugmentor/configs/__pycache__/position_config.cpython-310.pyc
imagedataaugmentor-1.0.3.dist-info/licenses/LICENSE
imagedataaugmentor-1.0.3.dist-info/METADATA
imagedataaugmentor-1.0.3.dist-info/WHEEL
imagedataaugmentor-1.0.3.dist-info/top_level.txt
imagedataaugmentor-1.0.3.dist-info/RECORD
