Metadata-Version: 2.4
Name: ImageDataAugmentor
Version: 1.0.3
Summary: Augment Image Data
Home-page: https://github.com/adityamangal1998/Image-Data-Augmentor.git
Author: Aditya Mangal
Author-email: adityamangal98@gmail.com
License: MIT
Classifier: License :: OSI Approved :: MIT License
Classifier: Programming Language :: Python :: 3
Classifier: Programming Language :: Python :: 3.7
License-File: LICENSE
Requires-Dist: opencv-python>=4.5
Requires-Dist: numpy>=1.17
Requires-Dist: future>=0.17
Requires-Dist: glob2>=0.7
Requires-Dist: ConcurrentImageRead>=0.0.10
Dynamic: author
Dynamic: author-email
Dynamic: classifier
Dynamic: description
Dynamic: description-content-type
Dynamic: home-page
Dynamic: license
Dynamic: license-file
Dynamic: requires-dist
Dynamic: summary
